[
  {
    "type": "spotify",
    "icon": "icon-spotify",
    "text": "links.spotify",
    "button": "primary",
    "link": "spotify:album:1qn9sJmcPGddxcMtvvrhZ6"
  },
  {
    "type": "appleMusic",
    "icon": "icon-apple-music",
    "text": "links.appleMusic",
    "button": "primary",
    "link": "https://music.apple.com/us/album/lo-siento-pero-no-single/1734913974"
  },
  {
    "type": "youtubeMusic",
    "icon": "icon-youtube-music",
    "text": "links.youtubeMusic",
    "button": "primary",
    "link": "https://music.youtube.com/playlist?list=OLAK5uy_lZIu8ors0gQmxUV5Se2HdnuUt_f9VtTe4"
  },
  {
    "type": "gig",
    "icon": "icon-gigs",
    "text": "links.tickets.20240525",
    "button": "secondary",
    "link": "https://www.wegow.com/us/concerts/concierto-de-nuevo-berlin-y-sweet-q-en-madrid"
  },
  {
    "type": "youtube",
    "icon": "icon-youtube",
    "text": "links.youtube.videoclip",
    "button": "secondary",
    "link": "https://www.youtube.com/watch?v=glVnYUQwPqE"
  },
  {
    "type": "youtube",
    "icon": "icon-youtube",
    "text": "links.youtube.cover",
    "button": "secondary",
    "link": "https://www.youtube.com/watch?v=p3gqyMh9CNg"
  }
]