[
  {
    "type": "info video fiesta",
    "title": "video.fiesta.title",
    "subtitle": "video.fiesta.subtitle",
    "text": "video.fiesta.text",
    "button": "video.fiesta.button",
    "icon": "icon-youtube",
    "youtubeHref": "https://www.youtube.com/watch?v=2FryW1MtBus"
  },
  {
    "type": "info gig g20250802",
    "title": "gigs.20250802.title",
    "subtitle": "gigs.20250802.date",
    "text": "gigs.20250802.text",
    "button": "gigs.20250802.button",
    "squared": true,
    "icon": "icon-gigs",
    "href": "https://sonoversofest.lariojaeventos.com/"
  }
]
